furiosa/common/__init__.py
furiosa/common/error.py
furiosa/common/git_version.txt
furiosa/common/native.py
furiosa/common/py.typed
furiosa/common/thread.py
furiosa/common/utils.py
furiosa/common/transport/__init__.py
furiosa/common/transport/base.py
furiosa/common/transport/error.py
furiosa/common/transport/file.py
furiosa/common/transport/github.py
furiosa/common/transport/http.py
furiosa/common/transport/s3.py
furiosa_common-0.10.2.dist-info/WHEEL
furiosa_common-0.10.2.dist-info/METADATA
furiosa_common-0.10.2.dist-info/RECORD
